Metadata-Version: 2.1
Name: qqr
Version: 1.0.0
Summary: A blazingly fast QR code restoration library for Python.
Home-page: https://github.com/weeebdev/qqr
Author: Author Name
Author-email: author.name@email.com
License: Apache
Project-URL: Documentation, https://weeebdev.github.io/qqr/
Project-URL: Source, https://github.com/weeebdev/qqr
Project-URL: Tracker, https://github.com/weeebdev/qqr/issues
Keywords: python template
Classifier: Development Status :: 4 - Beta
Classifier: License :: OSI Approved :: Apache Software License
Classifier: Intended Audience :: Science/Research
Classifier: Topic :: Scientific/Engineering
Classifier: Topic :: Scientific/Engineering :: Physics
Classifier: Programming Language :: Python :: 3
Classifier: Programming Language :: Python :: 3.6
Classifier: Programming Language :: Python :: 3.7
Classifier: Programming Language :: Python :: 3.8
Requires-Python: >=3.6
Provides-Extra: develop
Provides-Extra: complete
License-File: LICENSE
